bluesky_nats/__init__.py
bluesky_nats/_version.py
bluesky_nats/callbacks.py
bluesky_nats/filehandler.py
bluesky_nats/nats_client.py
bluesky_nats/nats_dispatcher.py
bluesky_nats/nats_publisher.py
bluesky_nats-0.1.4.dist-info/METADATA
bluesky_nats-0.1.4.dist-info/WHEEL
bluesky_nats-0.1.4.dist-info/licenses/LICENSE
bluesky_nats-0.1.4.dist-info/RECORD
