Metadata-Version: 2.4
Name: bluesky-nats
Version: 0.1.4
Summary: NATS JetStream connectivity for Bluesky
Project-URL: GitHub, https://github.com/Canadian-Light-Source/bluesky-nats
Author-email: Niko Kivel <niko.kivel@lightsource.ca>
Maintainer-email: "Canadian Lightsource Inc." <niko.kivel@lightsource.ca>
License:                     GNU GENERAL PUBLIC LICENSE
License-File: LICENSE
Classifier: Development Status :: 3 - Alpha
Classifier: License :: OSI Approved :: GNU General Public License v3 (GPLv3)
Classifier: Programming Language :: Python :: 3 :: Only
Classifier: Programming Language :: Python :: 3.10
Classifier: Programming Language :: Python :: 3.11
Classifier: Programming Language :: Python :: 3.12
Classifier: Topic :: Scientific/Engineering :: Physics
Requires-Python: >=3.10
Requires-Dist: bluesky>=1.12.0
Requires-Dist: nats-py>=2.9.0
Requires-Dist: ormsgpack>=1.5.0
Provides-Extra: examples
Requires-Dist: matplotlib>=3.9.2; extra == 'examples'
Requires-Dist: ophyd>=1.9.0; extra == 'examples'
